greycomp/__init__.py
greycomp-0.0.1.dist-info/LICENSE
greycomp-0.0.1.dist-info/METADATA
greycomp-0.0.1.dist-info/WHEEL
greycomp-0.0.1.dist-info/top_level.txt
greycomp-0.0.1.dist-info/RECORD
