Metadata-Version: 2.1
Name: greycomp
Version: 0.0.1
Summary: Greyscale Image Compression
Home-page: https://github.com/ThisIsNSH/Grey-Image-Compression
Author: Nishant Singh Hada
Author-email: hadanis.sing@gmail.com
License: UNKNOWN
Project-URL: Bug Tracker, https://github.com/ThisIsNSH/Grey-Image-Compression/issues
Platform: UNKNOWN
Classifier: Programming Language :: Python :: 3
Classifier: License :: OSI Approved :: MIT License
Classifier: Operating System :: OS Independent
Requires-Python: >=3.6
